SupaFileTree/__init__.py
SupaFileTree/ftree.py
SupaFileTree-0.2.0.dist-info/LICENSE
SupaFileTree-0.2.0.dist-info/METADATA
SupaFileTree-0.2.0.dist-info/WHEEL
SupaFileTree-0.2.0.dist-info/top_level.txt
SupaFileTree-0.2.0.dist-info/RECORD
