Metadata-Version: 2.1
Name: SupaFileTree
Version: 0.2.0
Summary: A project that when given a folder path, generates a tree of all the files inside
Author-email: Sainitin Daverpally <s.daverpally@gmail.com>
Project-URL: Homepage, https://github.com/SainitinD/File-Tree-Generator
Project-URL: Issues, https://github.com/SainitinD/File-Tree-Generator/issues
Classifier: Programming Language :: Python :: 3
Classifier: License :: OSI Approved :: MIT License
Classifier: Operating System :: OS Independent
Requires-Python: >=3.8
License-File: LICENSE
